wordhoard/.DS_Store
wordhoard/__init__.py
wordhoard/antonyms.py
wordhoard/dictionary.py
wordhoard/homophones.py
wordhoard/hypernyms.py
wordhoard/hyponyms.py
wordhoard/synonyms.py
wordhoard/__pycache__/__init__.cpython-39.pyc
wordhoard/__pycache__/antonyms.cpython-39.pyc
wordhoard/__pycache__/dictionary.cpython-39.pyc
wordhoard/__pycache__/homophones.cpython-39.pyc
wordhoard/__pycache__/hypernyms.cpython-39.pyc
wordhoard/__pycache__/hyponyms.cpython-39.pyc
wordhoard/__pycache__/synonyms.cpython-39.pyc
wordhoard/files/__init__.py
wordhoard/files/common_english_homophones.pkl
wordhoard/files/common_user_agents.pkl
wordhoard/files/no_homophones_english.pkl
wordhoard/utilities/__init__.py
wordhoard/utilities/caching.py
wordhoard/utilities/captcha_checker.py
wordhoard/utilities/cleansing.py
wordhoard/utilities/cloudflare_bypass.py
wordhoard/utilities/cloudflare_checker.py
wordhoard/utilities/colorized_text.py
wordhoard/utilities/deep_translator.py
wordhoard/utilities/email_address_verification.py
wordhoard/utilities/exceptions.py
wordhoard/utilities/google_translator.py
wordhoard/utilities/mymemory_translator.py
wordhoard/utilities/request_html.py
wordhoard/utilities/translator_languages.py
wordhoard/utilities/user_agents.py
wordhoard/utilities/word_verification.py
wordhoard/utilities/wordhoard_logger.py
wordhoard/utilities/__pycache__/__init__.cpython-39.pyc
wordhoard/utilities/__pycache__/caching.cpython-39.pyc
wordhoard/utilities/__pycache__/captcha_checker.cpython-39.pyc
wordhoard/utilities/__pycache__/cleansing.cpython-39.pyc
wordhoard/utilities/__pycache__/cloudflare_bypass.cpython-39.pyc
wordhoard/utilities/__pycache__/cloudflare_checker.cpython-39.pyc
wordhoard/utilities/__pycache__/colorized_text.cpython-39.pyc
wordhoard/utilities/__pycache__/deep_translator.cpython-39.pyc
wordhoard/utilities/__pycache__/email_address_verification.cpython-39.pyc
wordhoard/utilities/__pycache__/exceptions.cpython-39.pyc
wordhoard-1.5.5.dist-info/LICENSE
wordhoard-1.5.5.dist-info/METADATA
wordhoard-1.5.5.dist-info/WHEEL
wordhoard-1.5.5.dist-info/top_level.txt
wordhoard-1.5.5.dist-info/RECORD
