Metadata-Version: 2.1
Name: wordhoard
Version: 1.5.5
Summary: A comprehensive lexical discovery application that is useful for finding semantic relationships such as, the antonyms, synonyms, hypernyms, hyponyms, homophones and definitions for a specific word.
Home-page: https://github.com/johnbumgarner/wordhoard
Author: John Bumgarner
Author-email: wordhoardproject@gmail.com
License: LICENSE.txt
Keywords: antonyms,bag of words,definitions,hypernyms,hyponyms,homophones,information retrieval,lexicon,semantic relationships,synonyms,natural language processing
Classifier: Development Status :: 5 - Production/Stable
Classifier: Intended Audience :: Developers
Classifier: License :: OSI Approved :: MIT License
Classifier: Natural Language :: English
Classifier: Operating System :: OS Independent
Classifier: Programming Language :: Python :: 3.8
Classifier: Programming Language :: Python :: 3.9
Classifier: Programming Language :: Python :: 3.10
Classifier: Topic :: Software Development :: Libraries
Classifier: Topic :: Text Processing :: Linguistic
Classifier: Topic :: Utilities
Requires-Python: >=3.8
License-File: LICENSE
Requires-Dist: backoff >=2.2.1
Requires-Dist: beautifulsoup4 >=4.12.3
Requires-Dist: certifi >=2024.2.2
Requires-Dist: charset-normalizer >=3.3.2
Requires-Dist: cloudscraper >=1.2.71
Requires-Dist: deckar01-ratelimit >=3.0.2
Requires-Dist: deepl >=1.18.0
Requires-Dist: idna >=3.7
Requires-Dist: lxml >=5.2.2
Requires-Dist: pyparsing >=3.1.2
Requires-Dist: requests >=2.32.2
Requires-Dist: requests-toolbelt >=1.0.0
Requires-Dist: soupsieve >=2.5
Requires-Dist: urllib3 >=2.2.1
